cmreslogging/__init__.py
cmreslogging/handlers.py
cmreslogging/serializers.py
tests/__init__.py
tests/test_cmreshandler.py
tests/test_cmresserializer.py
CMRESHandler2-2.0.8.dist-info/LICENSE.md
CMRESHandler2-2.0.8.dist-info/METADATA
CMRESHandler2-2.0.8.dist-info/WHEEL
CMRESHandler2-2.0.8.dist-info/top_level.txt
CMRESHandler2-2.0.8.dist-info/RECORD
