Metadata-Version: 2.1
Name: CMRESHandler2
Version: 2.0.8
Summary: forked Elasticsearch Log handler for the logging library that includes session token support
Home-page: https://github.com/drumadrian/python-elasticsearch-logger
Author: Adrian Drummond
Author-email: adrian.drummond@gmail.com
License: Apache2
Keywords: logging elasticsearch handler log django instrumentation
Platform: UNKNOWN
Classifier: Development Status :: 5 - Production/Stable
Classifier: Intended Audience :: Developers
Classifier: Topic :: System :: Logging
Classifier: Topic :: Software Development :: Libraries
Classifier: Topic :: Internet :: Log Analysis
Classifier: License :: OSI Approved :: Apache Software License
Classifier: Programming Language :: Python :: 3.6
Requires-Dist: elasticsearch
Requires-Dist: requests
Provides-Extra: dev
Requires-Dist: check-manifest ; extra == 'dev'
Requires-Dist: six ; extra == 'dev'
Requires-Dist: pylint ; extra == 'dev'
Provides-Extra: test
Requires-Dist: coverage ; extra == 'test'
